lektor/__init__.py
lektor/__main__.py
lektor/assets.py
lektor/build_programs.py
lektor/builder.py
lektor/buildfailures.py
lektor/cli.py
lektor/cli_utils.py
lektor/constants.py
lektor/context.py
lektor/databags.py
lektor/datamodel.py
lektor/db.py
lektor/devcli.py
lektor/devserver.py
lektor/editor.py
lektor/exception.py
lektor/filecontents.py
lektor/i18n.py
lektor/imagetools.py
lektor/markdown.py
lektor/metaformat.py
lektor/packages.py
lektor/pagination.py
lektor/pluginsystem.py
lektor/project.py
lektor/publisher.py
lektor/quickstart.py
lektor/reporter.py
lektor/sourceobj.py
lektor/sourcesearch.py
lektor/utils.py
lektor/videotools.py
lektor/watcher.py
lektor/admin/__init__.py
lektor/admin/utils.py
lektor/admin/webui.py
lektor/admin/modules/__init__.py
lektor/admin/modules/api.py
lektor/admin/modules/common.py
lektor/admin/modules/dash.py
lektor/admin/modules/serve.py
lektor/admin/static/115e1ff1541e73082abf.woff
lektor/admin/static/1e59d2330b4c6deb84b3.ttf
lektor/admin/static/20fd1704ea223900efa9.woff2
lektor/admin/static/56161bdcd33f55fdcef7.woff
lektor/admin/static/7d5012096466e7279f2b.woff2
lektor/admin/static/8b43027f47b20503057d.eot
lektor/admin/static/app.css
lektor/admin/static/app.css.map
lektor/admin/static/app.js
lektor/admin/static/app.js.map
lektor/admin/static/b2545b9e857b33e75fdc.woff2
lektor/admin/static/c1e38fd9e0e74ba58f7a.svg
lektor/admin/static/f691f37e57f04c152e23.woff
lektor/admin/static/vendor.css
lektor/admin/static/vendor.css.map
lektor/admin/static/vendor.js
lektor/admin/static/vendor.js.map
lektor/admin/templates/base.html
lektor/admin/templates/build-failure.html
lektor/admin/templates/dash.html
lektor/admin/templates/layout.html
lektor/environment/__init__.py
lektor/environment/config.py
lektor/environment/expressions.py
lektor/quickstart-templates/plugin/.gitignore.in
lektor/quickstart-templates/plugin/@plugin_module@.py.in
lektor/quickstart-templates/plugin/README.md.in
lektor/quickstart-templates/plugin/setup.cfg.in
Lektor-3.3.12.dist-info/LICENSE
Lektor-3.3.12.dist-info/METADATA
Lektor-3.3.12.dist-info/WHEEL
Lektor-3.3.12.dist-info/entry_points.txt
Lektor-3.3.12.dist-info/top_level.txt
Lektor-3.3.12.dist-info/RECORD
