Metadata-Version: 2.1
Name: Lektor
Version: 3.3.12
Summary: A static content management system.
Home-page: https://www.getlektor.com/
Author: Armin Ronacher
Author-email: armin.ronacher@active-4.com
License: BSD
Project-URL: Homepage, https://www.getlektor.com/
Project-URL: Source, https://github.com/lektor/lektor/
Project-URL: Documentation, https://www.getlektor.com/docs/
Project-URL: Changelog, https://github.com/lektor/lektor/blob/3.3-maintenance/CHANGES.md
Platform: any
Classifier: Framework :: Lektor
Classifier: Environment :: Web Environment
Classifier: Intended Audience :: Developers
Classifier: License :: OSI Approved :: BSD License
Classifier: Operating System :: OS Independent
Classifier: Programming Language :: Python
Classifier: Programming Language :: Python :: 3
Classifier: Programming Language :: Python :: 3.6
Classifier: Programming Language :: Python :: 3.7
Classifier: Programming Language :: Python :: 3.8
Classifier: Programming Language :: Python :: 3.9
Classifier: Programming Language :: Python :: 3.10
Classifier: Programming Language :: Python :: 3.11
Classifier: Programming Language :: Python :: 3.12
Classifier: Topic :: Internet :: WWW/HTTP :: Dynamic Content
Classifier: Topic :: Software Development :: Libraries :: Python Modules
Requires-Python: >=3.6
License-File: LICENSE
Requires-Dist: Babel
Requires-Dist: click >=6.0
Requires-Dist: EXIFRead
Requires-Dist: filetype >=1.0.7
Requires-Dist: Flask
Requires-Dist: inifile >=0.4.1
Requires-Dist: Jinja2 >=3.0
Requires-Dist: markupsafe
Requires-Dist: mistune <2,>=0.7.0
Requires-Dist: pip >=21.1
Requires-Dist: python-slugify
Requires-Dist: pytz
Requires-Dist: requests
Requires-Dist: setuptools >=45.2
Requires-Dist: watchdog
Requires-Dist: Werkzeug <2.4
Provides-Extra: ipython
Requires-Dist: ipython ; extra == 'ipython'
Requires-Dist: traitlets ; extra == 'ipython'
